kontxt/__init__.py
kontxt/__main__.py
kontxt/cli.py
kontxt/py.typed
kontxt/adapters/__init__.py
kontxt/adapters/llm/__init__.py
kontxt/adapters/llm/echo.py
kontxt/backends/__init__.py
kontxt/events/__init__.py
kontxt/events/events.py
kontxt/memory/__init__.py
kontxt/memory/memory_manager.py
kontxt/policies/__init__.py
kontxt/policies/policy_engine.py
kontxt/registry/__init__.py
kontxt/registry/prompt_registry.py
kontxt/store/__init__.py
kontxt/store/context_store.py
kontxt/summarizer/__init__.py
kontxt/summarizer/summarizer.py
kontxt/utils/__init__.py
kontxt/utils/ids.py
kontxt/utils/tokens.py
kontxt-0.1.0.dist-info/METADATA
kontxt-0.1.0.dist-info/WHEEL
kontxt-0.1.0.dist-info/entry_points.txt
kontxt-0.1.0.dist-info/licenses/LICENSE
kontxt-0.1.0.dist-info/RECORD
