Metadata-Version: 2.4
Name: kontxt
Version: 0.1.0
Summary: Framework-agnostic context management for AI applications (early alpha).
Author-email: Elvin Gomez <3lv27.dev@gmail.com>
License: Apache-2.0
License-File: LICENSE
Classifier: Development Status :: 3 - Alpha
Classifier: Intended Audience :: Developers
Classifier: License :: OSI Approved :: Apache Software License
Classifier: Programming Language :: Python :: 3.11
Classifier: Programming Language :: Python :: 3.12
Requires-Python: >=3.11
